ry_pg_utils/__init__.py
ry_pg_utils/config.py
ry_pg_utils/connect.py
ry_pg_utils/dynamic_table.py
ry_pg_utils/notify_trigger.py
ry_pg_utils/parse_args.py
ry_pg_utils/postgres_info.py
ry_pg_utils/py.typed
ry_pg_utils/updater.py
ry_pg_utils/ipc/__init__.py
ry_pg_utils/ipc/channels.py
ry_pg_utils/pb_types/__init__.py
ry_pg_utils/pb_types/database_pb2.py
ry_pg_utils/pb_types/database_pb2.pyi
ry_pg_utils/pb_types/py.typed
ry_pg_utils/tools/__init__.py
ry_pg_utils/tools/db_query.py
ry_pg_utils-3.0.8.dist-info/licenses/LICENSE
ry_pg_utils-3.0.8.dist-info/METADATA
ry_pg_utils-3.0.8.dist-info/WHEEL
ry_pg_utils-3.0.8.dist-info/top_level.txt
ry_pg_utils-3.0.8.dist-info/RECORD
