Metadata-Version: 2.4
Name: ry-pg-utils
Version: 3.0.8
Summary: Utility functions for PostgreSQL
Author: Ross Yeager
Author-email: ryeager12@email.com
Classifier: Development Status :: 5 - Production/Stable
Classifier: Intended Audience :: Developers
Classifier: License :: OSI Approved :: MIT License
Classifier: Programming Language :: Python :: 3
Classifier: Programming Language :: Python :: 3.12
License-File: LICENSE
Requires-Dist: ry_redis_bus
Requires-Dist: ryutils
Requires-Dist: sqlalchemy
Requires-Dist: sqlalchemy_utils
Requires-Dist: psycopg2-binary
Requires-Dist: python-dotenv
Requires-Dist: tenacity
Requires-Dist: types-protobuf
Requires-Dist: types-psycopg2
Dynamic: author
Dynamic: author-email
Dynamic: classifier
Dynamic: description
Dynamic: description-content-type
Dynamic: license-file
Dynamic: requires-dist
Dynamic: summary
